pdf_processor/__init__.py
pdf_processor/pdf_processor.py
pdf_processor-0.1.dist-info/LICENSE
pdf_processor-0.1.dist-info/METADATA
pdf_processor-0.1.dist-info/WHEEL
pdf_processor-0.1.dist-info/entry_points.txt
pdf_processor-0.1.dist-info/top_level.txt
pdf_processor-0.1.dist-info/RECORD
