Metadata-Version: 2.1
Name: pdf_processor
Version: 0.1
Summary: A PDF processing package to convert PDF to images and adjust their brightness and contrast.
Home-page: https://github.com/lvchenjia/pdf-toolkit
Author: Xun Qin
Author-email: lvchenjia2050@gmail.com
Classifier: Programming Language :: Python :: 3
Classifier: License :: OSI Approved :: MIT License
Classifier: Operating System :: OS Independent
Requires-Python: >=3.6
License-File: LICENSE
Requires-Dist: pymupdf
Requires-Dist: Pillow
